MANIFEST.in
README.md
requirements.txt
setup.py
cortical_layers/LayerPredictor.py
cortical_layers/Minnie_soma_nuc_feature_model_83_1.pkl
cortical_layers/SublayerPredictor.py
cortical_layers/__init__.py
cortical_layers/minnie65_full_prediction.json
cortical_layers/minnie65_sub6_full_prediction.json
cortical_layers/smooth_minnie65_full_prediction.json
cortical_layers/smooth_minnie65_sub6_full_prediction.json
cortical_layers.egg-info/PKG-INFO
cortical_layers.egg-info/SOURCES.txt
cortical_layers.egg-info/dependency_links.txt
cortical_layers.egg-info/requires.txt
cortical_layers.egg-info/top_level.txt
cortical_layers/__pycache__/LayerPredictor.cpython-37.pyc
cortical_layers/__pycache__/SublayerPredictor.cpython-37.pyc
cortical_layers/__pycache__/__init__.cpython-37.pyc