Metadata-Version: 1.0
Name: cortical-layers
Version: 0.2.1
Summary: a tool to interact with cortical layer labels of MICrONS EM segmentation data
Home-page: https://github.com/AllenInstitute/cortical-layers
Author: Alex Mallen
Author-email: atmallen@uw.edu,
License: UNKNOWN
Platform: UNKNOWN
